[
  {
    "name": "Fremskrittspartiet",
    "id": "frp",
    "url": "https://www.frp.no",
    "date": "2021-04-16T00:53:54.719Z",
    "timeStamp": 1618534434719,
    "result": [
      {
        "id": "performance",
        "title": "Performance",
        "score": 48
      },
      {
        "id": "accessibility",
        "title": "Accessibility",
        "description": "These checks highlight opportunities to [improve the accessibility of your web app](https://developers.google.com/web/fundamentals/accessibility). Only a subset of accessibility issues can be automatically detected so manual testing is also encouraged.",
        "score": 99,
        "manualDescription": "These items address areas which an automated testing tool cannot cover. Learn more in our guide on [conducting an accessibility review](https://developers.google.com/web/fundamentals/accessibility/how-to-review)."
      },
      {
        "id": "best-practices",
        "title": "Best Practices",
        "score": 100
      },
      {
        "id": "seo",
        "title": "SEO",
        "description": "These checks ensure that your page is optimized for search engine results ranking. There are additional factors Lighthouse does not check that may affect your search ranking. [Learn more](https://support.google.com/webmasters/answer/35769).",
        "score": 100,
        "manualDescription": "Run these additional validators on your site to check additional SEO best practices."
      },
      {
        "id": "securityheaders",
        "title": "Security",
        "score": 0,
        "grade": "F",
        "description": "Security Headers https://securityheaders.com is created by Scott Helme https://scotthelme.co.uk/ to drive up the usage of security based headers across the web."
      }
    ]
  },
  {
    "name": "Venstre",
    "id": "venstre",
    "url": "https://www.venstre.no",
    "date": "2021-04-16T00:54:10.941Z",
    "timeStamp": 1618534450941,
    "result": [
      {
        "id": "performance",
        "title": "Performance",
        "score": 34
      },
      {
        "id": "accessibility",
        "title": "Accessibility",
        "description": "These checks highlight opportunities to [improve the accessibility of your web app](https://developers.google.com/web/fundamentals/accessibility). Only a subset of accessibility issues can be automatically detected so manual testing is also encouraged.",
        "score": 89,
        "manualDescription": "These items address areas which an automated testing tool cannot cover. Learn more in our guide on [conducting an accessibility review](https://developers.google.com/web/fundamentals/accessibility/how-to-review)."
      },
      {
        "id": "best-practices",
        "title": "Best Practices",
        "score": 87
      },
      {
        "id": "seo",
        "title": "SEO",
        "description": "These checks ensure that your page is optimized for search engine results ranking. There are additional factors Lighthouse does not check that may affect your search ranking. [Learn more](https://support.google.com/webmasters/answer/35769).",
        "score": 92,
        "manualDescription": "Run these additional validators on your site to check additional SEO best practices."
      },
      {
        "id": "securityheaders",
        "title": "Security",
        "score": 50,
        "grade": "D",
        "description": "Security Headers https://securityheaders.com is created by Scott Helme https://scotthelme.co.uk/ to drive up the usage of security based headers across the web."
      }
    ]
  },
  {
    "name": "Høyre",
    "id": "hoyre",
    "url": "https://hoyre.no",
    "date": "2021-04-16T00:54:31.805Z",
    "timeStamp": 1618534471805,
    "result": [
      {
        "id": "performance",
        "title": "Performance",
        "score": 33
      },
      {
        "id": "accessibility",
        "title": "Accessibility",
        "description": "These checks highlight opportunities to [improve the accessibility of your web app](https://developers.google.com/web/fundamentals/accessibility). Only a subset of accessibility issues can be automatically detected so manual testing is also encouraged.",
        "score": 98,
        "manualDescription": "These items address areas which an automated testing tool cannot cover. Learn more in our guide on [conducting an accessibility review](https://developers.google.com/web/fundamentals/accessibility/how-to-review)."
      },
      {
        "id": "best-practices",
        "title": "Best Practices",
        "score": 93
      },
      {
        "id": "seo",
        "title": "SEO",
        "description": "These checks ensure that your page is optimized for search engine results ranking. There are additional factors Lighthouse does not check that may affect your search ranking. [Learn more](https://support.google.com/webmasters/answer/35769).",
        "score": 99,
        "manualDescription": "Run these additional validators on your site to check additional SEO best practices."
      },
      {
        "id": "securityheaders",
        "title": "Security",
        "score": 65,
        "grade": "C",
        "description": "Security Headers https://securityheaders.com is created by Scott Helme https://scotthelme.co.uk/ to drive up the usage of security based headers across the web."
      }
    ]
  },
  {
    "name": "Miljøpartiet De Grønne",
    "id": "mdg",
    "url": "https://mdg.no",
    "date": "2021-04-16T00:54:50.500Z",
    "timeStamp": 1618534490500,
    "result": [
      {
        "id": "performance",
        "title": "Performance",
        "score": 18
      },
      {
        "id": "accessibility",
        "title": "Accessibility",
        "description": "These checks highlight opportunities to [improve the accessibility of your web app](https://developers.google.com/web/fundamentals/accessibility). Only a subset of accessibility issues can be automatically detected so manual testing is also encouraged.",
        "score": 82,
        "manualDescription": "These items address areas which an automated testing tool cannot cover. Learn more in our guide on [conducting an accessibility review](https://developers.google.com/web/fundamentals/accessibility/how-to-review)."
      },
      {
        "id": "best-practices",
        "title": "Best Practices",
        "score": 73
      },
      {
        "id": "seo",
        "title": "SEO",
        "description": "These checks ensure that your page is optimized for search engine results ranking. There are additional factors Lighthouse does not check that may affect your search ranking. [Learn more](https://support.google.com/webmasters/answer/35769).",
        "score": 86,
        "manualDescription": "Run these additional validators on your site to check additional SEO best practices."
      },
      {
        "id": "securityheaders",
        "title": "Security",
        "score": 50,
        "grade": "D",
        "description": "Security Headers https://securityheaders.com is created by Scott Helme https://scotthelme.co.uk/ to drive up the usage of security based headers across the web."
      }
    ]
  },
  {
    "name": "Senterpartiet",
    "id": "sp",
    "url": "https://www.senterpartiet.no",
    "date": "2021-04-16T00:55:15.462Z",
    "timeStamp": 1618534515462,
    "result": [
      {
        "id": "performance",
        "title": "Performance",
        "score": 56
      },
      {
        "id": "accessibility",
        "title": "Accessibility",
        "description": "These checks highlight opportunities to [improve the accessibility of your web app](https://developers.google.com/web/fundamentals/accessibility). Only a subset of accessibility issues can be automatically detected so manual testing is also encouraged.",
        "score": 91,
        "manualDescription": "These items address areas which an automated testing tool cannot cover. Learn more in our guide on [conducting an accessibility review](https://developers.google.com/web/fundamentals/accessibility/how-to-review)."
      },
      {
        "id": "best-practices",
        "title": "Best Practices",
        "score": 100
      },
      {
        "id": "seo",
        "title": "SEO",
        "description": "These checks ensure that your page is optimized for search engine results ranking. There are additional factors Lighthouse does not check that may affect your search ranking. [Learn more](https://support.google.com/webmasters/answer/35769).",
        "score": 100,
        "manualDescription": "Run these additional validators on your site to check additional SEO best practices."
      },
      {
        "id": "securityheaders",
        "title": "Security",
        "score": 0,
        "grade": "F",
        "description": "Security Headers https://securityheaders.com is created by Scott Helme https://scotthelme.co.uk/ to drive up the usage of security based headers across the web."
      }
    ]
  },
  {
    "name": "Kristelig Folkeparti",
    "id": "krf",
    "url": "https://www.krf.no",
    "date": "2021-04-16T00:55:51.637Z",
    "timeStamp": 1618534551637,
    "result": [
      {
        "id": "performance",
        "title": "Performance",
        "score": 86
      },
      {
        "id": "accessibility",
        "title": "Accessibility",
        "description": "These checks highlight opportunities to [improve the accessibility of your web app](https://developers.google.com/web/fundamentals/accessibility). Only a subset of accessibility issues can be automatically detected so manual testing is also encouraged.",
        "score": 100,
        "manualDescription": "These items address areas which an automated testing tool cannot cover. Learn more in our guide on [conducting an accessibility review](https://developers.google.com/web/fundamentals/accessibility/how-to-review)."
      },
      {
        "id": "best-practices",
        "title": "Best Practices",
        "score": 100
      },
      {
        "id": "seo",
        "title": "SEO",
        "description": "These checks ensure that your page is optimized for search engine results ranking. There are additional factors Lighthouse does not check that may affect your search ranking. [Learn more](https://support.google.com/webmasters/answer/35769).",
        "score": 100,
        "manualDescription": "Run these additional validators on your site to check additional SEO best practices."
      },
      {
        "id": "securityheaders",
        "title": "Security",
        "score": 65,
        "grade": "C",
        "description": "Security Headers https://securityheaders.com is created by Scott Helme https://scotthelme.co.uk/ to drive up the usage of security based headers across the web."
      }
    ]
  },
  {
    "name": "SV",
    "id": "sv",
    "url": "https://www.sv.no",
    "date": "2021-04-16T00:56:23.568Z",
    "timeStamp": 1618534583568,
    "result": [
      {
        "id": "performance",
        "title": "Performance",
        "score": 59
      },
      {
        "id": "accessibility",
        "title": "Accessibility",
        "description": "These checks highlight opportunities to [improve the accessibility of your web app](https://developers.google.com/web/fundamentals/accessibility). Only a subset of accessibility issues can be automatically detected so manual testing is also encouraged.",
        "score": 97,
        "manualDescription": "These items address areas which an automated testing tool cannot cover. Learn more in our guide on [conducting an accessibility review](https://developers.google.com/web/fundamentals/accessibility/how-to-review)."
      },
      {
        "id": "best-practices",
        "title": "Best Practices",
        "score": 93
      },
      {
        "id": "seo",
        "title": "SEO",
        "description": "These checks ensure that your page is optimized for search engine results ranking. There are additional factors Lighthouse does not check that may affect your search ranking. [Learn more](https://support.google.com/webmasters/answer/35769).",
        "score": 86,
        "manualDescription": "Run these additional validators on your site to check additional SEO best practices."
      },
      {
        "id": "securityheaders",
        "title": "Security",
        "score": 95,
        "grade": "A",
        "description": "Security Headers https://securityheaders.com is created by Scott Helme https://scotthelme.co.uk/ to drive up the usage of security based headers across the web."
      }
    ]
  },
  {
    "name": "Arbeiderpartiet",
    "id": "ap",
    "url": "https://www.arbeiderpartiet.no",
    "date": "2021-04-16T00:56:45.172Z",
    "timeStamp": 1618534605172,
    "result": [
      {
        "id": "performance",
        "title": "Performance",
        "score": 48
      },
      {
        "id": "accessibility",
        "title": "Accessibility",
        "description": "These checks highlight opportunities to [improve the accessibility of your web app](https://developers.google.com/web/fundamentals/accessibility). Only a subset of accessibility issues can be automatically detected so manual testing is also encouraged.",
        "score": 94,
        "manualDescription": "These items address areas which an automated testing tool cannot cover. Learn more in our guide on [conducting an accessibility review](https://developers.google.com/web/fundamentals/accessibility/how-to-review)."
      },
      {
        "id": "best-practices",
        "title": "Best Practices",
        "score": 87
      },
      {
        "id": "seo",
        "title": "SEO",
        "description": "These checks ensure that your page is optimized for search engine results ranking. There are additional factors Lighthouse does not check that may affect your search ranking. [Learn more](https://support.google.com/webmasters/answer/35769).",
        "score": 98,
        "manualDescription": "Run these additional validators on your site to check additional SEO best practices."
      },
      {
        "id": "securityheaders",
        "title": "Security",
        "score": 50,
        "grade": "D",
        "description": "Security Headers https://securityheaders.com is created by Scott Helme https://scotthelme.co.uk/ to drive up the usage of security based headers across the web."
      }
    ]
  },
  {
    "id": "raudt",
    "name": "Rødt",
    "url": "https://xn--rdt-0na.no",
    "date": "2021-04-16T00:57:12.042Z",
    "timeStamp": 1618534632042,
    "result": [
      {
        "id": "performance",
        "title": "Performance",
        "score": 64
      },
      {
        "id": "accessibility",
        "title": "Accessibility",
        "description": "These checks highlight opportunities to [improve the accessibility of your web app](https://developers.google.com/web/fundamentals/accessibility). Only a subset of accessibility issues can be automatically detected so manual testing is also encouraged.",
        "score": 97,
        "manualDescription": "These items address areas which an automated testing tool cannot cover. Learn more in our guide on [conducting an accessibility review](https://developers.google.com/web/fundamentals/accessibility/how-to-review)."
      },
      {
        "id": "best-practices",
        "title": "Best Practices",
        "score": 93
      },
      {
        "id": "seo",
        "title": "SEO",
        "description": "These checks ensure that your page is optimized for search engine results ranking. There are additional factors Lighthouse does not check that may affect your search ranking. [Learn more](https://support.google.com/webmasters/answer/35769).",
        "score": 98,
        "manualDescription": "Run these additional validators on your site to check additional SEO best practices."
      },
      {
        "id": "securityheaders",
        "title": "Security",
        "score": 95,
        "grade": "A",
        "description": "Security Headers https://securityheaders.com is created by Scott Helme https://scotthelme.co.uk/ to drive up the usage of security based headers across the web."
      }
    ]
  }
]