[
  {
    "name": "Ålesund",
    "id": "alesund",
    "url": "https://www.alesund.kommune.no",
    "date": "2019-04-26T00:26:28.901Z",
    "timeStamp": 1556238388901,
    "result": [
      {
        "id": "performance",
        "title": "Performance",
        "score": 35
      },
      {
        "id": "accessibility",
        "title": "Accessibility",
        "description": "These checks highlight opportunities to [improve the accessibility of your web app](https://developers.google.com/web/fundamentals/accessibility). Only a subset of accessibility issues can be automatically detected so manual testing is also encouraged.",
        "score": 63,
        "manualDescription": "These items address areas which an automated testing tool cannot cover. Learn more in our guide on [conducting an accessibility review](https://developers.google.com/web/fundamentals/accessibility/how-to-review)."
      },
      {
        "id": "best-practices",
        "title": "Best Practices",
        "score": 77
      },
      {
        "id": "seo",
        "title": "SEO",
        "description": "These checks ensure that your page is optimized for search engine results ranking. There are additional factors Lighthouse does not check that may affect your search ranking. [Learn more](https://support.google.com/webmasters/answer/35769).",
        "score": 98,
        "manualDescription": "Run these additional validators on your site to check additional SEO best practices."
      },
      {
        "id": "observatory",
        "title": "Security",
        "score": 0,
        "grade": "F",
        "description": "The Mozilla Observatory teaches you how to configure your sites safely and securely. https://observatory.mozilla.org"
      }
    ]
  },
  {
    "name": "Trondheim",
    "id": "trondheim",
    "url": "https://www.trondheim.kommune.no",
    "date": "2019-04-26T00:26:47.791Z",
    "timeStamp": 1556238407791,
    "result": [
      {
        "id": "performance",
        "title": "Performance",
        "score": 64
      },
      {
        "id": "accessibility",
        "title": "Accessibility",
        "description": "These checks highlight opportunities to [improve the accessibility of your web app](https://developers.google.com/web/fundamentals/accessibility). Only a subset of accessibility issues can be automatically detected so manual testing is also encouraged.",
        "score": 78,
        "manualDescription": "These items address areas which an automated testing tool cannot cover. Learn more in our guide on [conducting an accessibility review](https://developers.google.com/web/fundamentals/accessibility/how-to-review)."
      },
      {
        "id": "best-practices",
        "title": "Best Practices",
        "score": 92
      },
      {
        "id": "seo",
        "title": "SEO",
        "description": "These checks ensure that your page is optimized for search engine results ranking. There are additional factors Lighthouse does not check that may affect your search ranking. [Learn more](https://support.google.com/webmasters/answer/35769).",
        "score": 100,
        "manualDescription": "Run these additional validators on your site to check additional SEO best practices."
      },
      {
        "id": "observatory",
        "title": "Security",
        "score": 0,
        "grade": "F",
        "description": "The Mozilla Observatory teaches you how to configure your sites safely and securely. https://observatory.mozilla.org"
      }
    ]
  },
  {
    "name": "Stavanger",
    "id": "stavanger",
    "url": "https://www.stavanger.kommune.no",
    "date": "2019-04-26T00:28:57.044Z",
    "timeStamp": 1556238537044,
    "result": [
      {
        "id": "performance",
        "title": "Performance",
        "score": 50
      },
      {
        "id": "accessibility",
        "title": "Accessibility",
        "description": "These checks highlight opportunities to [improve the accessibility of your web app](https://developers.google.com/web/fundamentals/accessibility). Only a subset of accessibility issues can be automatically detected so manual testing is also encouraged.",
        "score": 100,
        "manualDescription": "These items address areas which an automated testing tool cannot cover. Learn more in our guide on [conducting an accessibility review](https://developers.google.com/web/fundamentals/accessibility/how-to-review)."
      },
      {
        "id": "best-practices",
        "title": "Best Practices",
        "score": 85
      },
      {
        "id": "seo",
        "title": "SEO",
        "description": "These checks ensure that your page is optimized for search engine results ranking. There are additional factors Lighthouse does not check that may affect your search ranking. [Learn more](https://support.google.com/webmasters/answer/35769).",
        "score": 96,
        "manualDescription": "Run these additional validators on your site to check additional SEO best practices."
      },
      {
        "id": "observatory",
        "title": "Security",
        "score": 0,
        "grade": "F",
        "description": "The Mozilla Observatory teaches you how to configure your sites safely and securely. https://observatory.mozilla.org"
      }
    ]
  },
  {
    "name": "Sandnes",
    "id": "sandnes",
    "url": "https://www.sandnes.kommune.no",
    "date": "2019-04-26T00:29:11.005Z",
    "timeStamp": 1556238551005,
    "result": [
      {
        "id": "performance",
        "title": "Performance",
        "score": 2
      },
      {
        "id": "accessibility",
        "title": "Accessibility",
        "description": "These checks highlight opportunities to [improve the accessibility of your web app](https://developers.google.com/web/fundamentals/accessibility). Only a subset of accessibility issues can be automatically detected so manual testing is also encouraged.",
        "score": 62,
        "manualDescription": "These items address areas which an automated testing tool cannot cover. Learn more in our guide on [conducting an accessibility review](https://developers.google.com/web/fundamentals/accessibility/how-to-review)."
      },
      {
        "id": "best-practices",
        "title": "Best Practices",
        "score": 85
      },
      {
        "id": "seo",
        "title": "SEO",
        "description": "These checks ensure that your page is optimized for search engine results ranking. There are additional factors Lighthouse does not check that may affect your search ranking. [Learn more](https://support.google.com/webmasters/answer/35769).",
        "score": 88,
        "manualDescription": "Run these additional validators on your site to check additional SEO best practices."
      },
      {
        "id": "observatory",
        "title": "Security",
        "score": 0,
        "grade": "F",
        "description": "The Mozilla Observatory teaches you how to configure your sites safely and securely. https://observatory.mozilla.org"
      }
    ]
  },
  {
    "name": "Oslo",
    "id": "oslo",
    "url": "https://www.oslo.kommune.no",
    "date": "2019-04-26T00:29:35.403Z",
    "timeStamp": 1556238575403,
    "result": [
      {
        "id": "performance",
        "title": "Performance",
        "score": 7
      },
      {
        "id": "accessibility",
        "title": "Accessibility",
        "description": "These checks highlight opportunities to [improve the accessibility of your web app](https://developers.google.com/web/fundamentals/accessibility). Only a subset of accessibility issues can be automatically detected so manual testing is also encouraged.",
        "score": 83,
        "manualDescription": "These items address areas which an automated testing tool cannot cover. Learn more in our guide on [conducting an accessibility review](https://developers.google.com/web/fundamentals/accessibility/how-to-review)."
      },
      {
        "id": "best-practices",
        "title": "Best Practices",
        "score": 92
      },
      {
        "id": "seo",
        "title": "SEO",
        "description": "These checks ensure that your page is optimized for search engine results ranking. There are additional factors Lighthouse does not check that may affect your search ranking. [Learn more](https://support.google.com/webmasters/answer/35769).",
        "score": 96,
        "manualDescription": "Run these additional validators on your site to check additional SEO best practices."
      },
      {
        "id": "observatory",
        "title": "Security",
        "score": 0,
        "grade": "F",
        "description": "The Mozilla Observatory teaches you how to configure your sites safely and securely. https://observatory.mozilla.org"
      }
    ]
  },
  {
    "name": "Narvik",
    "id": "narvik",
    "url": "https://www.narvik.kommune.no",
    "date": "2019-04-26T00:29:56.817Z",
    "timeStamp": 1556238596817,
    "result": [
      {
        "id": "performance",
        "title": "Performance",
        "score": 55
      },
      {
        "id": "accessibility",
        "title": "Accessibility",
        "description": "These checks highlight opportunities to [improve the accessibility of your web app](https://developers.google.com/web/fundamentals/accessibility). Only a subset of accessibility issues can be automatically detected so manual testing is also encouraged.",
        "score": 82,
        "manualDescription": "These items address areas which an automated testing tool cannot cover. Learn more in our guide on [conducting an accessibility review](https://developers.google.com/web/fundamentals/accessibility/how-to-review)."
      },
      {
        "id": "best-practices",
        "title": "Best Practices",
        "score": 77
      },
      {
        "id": "seo",
        "title": "SEO",
        "description": "These checks ensure that your page is optimized for search engine results ranking. There are additional factors Lighthouse does not check that may affect your search ranking. [Learn more](https://support.google.com/webmasters/answer/35769).",
        "score": 100,
        "manualDescription": "Run these additional validators on your site to check additional SEO best practices."
      },
      {
        "id": "observatory",
        "title": "Security",
        "score": 0,
        "grade": "F",
        "description": "The Mozilla Observatory teaches you how to configure your sites safely and securely. https://observatory.mozilla.org"
      }
    ]
  },
  {
    "name": "Kristiansand",
    "id": "kristiansand",
    "url": "https://www.kristiansand.kommune.no",
    "date": "2019-04-26T00:30:11.089Z",
    "timeStamp": 1556238611089,
    "result": [
      {
        "id": "performance",
        "title": "Performance",
        "score": 38
      },
      {
        "id": "accessibility",
        "title": "Accessibility",
        "description": "These checks highlight opportunities to [improve the accessibility of your web app](https://developers.google.com/web/fundamentals/accessibility). Only a subset of accessibility issues can be automatically detected so manual testing is also encouraged.",
        "score": 80,
        "manualDescription": "These items address areas which an automated testing tool cannot cover. Learn more in our guide on [conducting an accessibility review](https://developers.google.com/web/fundamentals/accessibility/how-to-review)."
      },
      {
        "id": "best-practices",
        "title": "Best Practices",
        "score": 85
      },
      {
        "id": "seo",
        "title": "SEO",
        "description": "These checks ensure that your page is optimized for search engine results ranking. There are additional factors Lighthouse does not check that may affect your search ranking. [Learn more](https://support.google.com/webmasters/answer/35769).",
        "score": 89,
        "manualDescription": "Run these additional validators on your site to check additional SEO best practices."
      },
      {
        "id": "observatory",
        "title": "Security",
        "score": 0,
        "grade": "F",
        "description": "The Mozilla Observatory teaches you how to configure your sites safely and securely. https://observatory.mozilla.org"
      }
    ]
  },
  {
    "id": "halden",
    "name": "Halden",
    "url": "https://www.halden.kommune.no",
    "date": "2019-04-26T00:30:28.197Z",
    "timeStamp": 1556238628197,
    "result": [
      {
        "id": "performance",
        "title": "Performance",
        "score": 7
      },
      {
        "id": "accessibility",
        "title": "Accessibility",
        "description": "These checks highlight opportunities to [improve the accessibility of your web app](https://developers.google.com/web/fundamentals/accessibility). Only a subset of accessibility issues can be automatically detected so manual testing is also encouraged.",
        "score": 81,
        "manualDescription": "These items address areas which an automated testing tool cannot cover. Learn more in our guide on [conducting an accessibility review](https://developers.google.com/web/fundamentals/accessibility/how-to-review)."
      },
      {
        "id": "best-practices",
        "title": "Best Practices",
        "score": 85
      },
      {
        "id": "seo",
        "title": "SEO",
        "description": "These checks ensure that your page is optimized for search engine results ranking. There are additional factors Lighthouse does not check that may affect your search ranking. [Learn more](https://support.google.com/webmasters/answer/35769).",
        "score": 60,
        "manualDescription": "Run these additional validators on your site to check additional SEO best practices."
      },
      {
        "id": "observatory",
        "title": "Security",
        "score": 60,
        "grade": "C-",
        "description": "The Mozilla Observatory teaches you how to configure your sites safely and securely. https://observatory.mozilla.org"
      }
    ]
  },
  {
    "id": "drammen",
    "name": "Drammen",
    "url": "https://www.drammen.kommune.no",
    "date": "2019-04-26T00:31:02.114Z",
    "timeStamp": 1556238662114,
    "result": [
      {
        "id": "performance",
        "title": "Performance",
        "score": 62
      },
      {
        "id": "accessibility",
        "title": "Accessibility",
        "description": "These checks highlight opportunities to [improve the accessibility of your web app](https://developers.google.com/web/fundamentals/accessibility). Only a subset of accessibility issues can be automatically detected so manual testing is also encouraged.",
        "score": 77,
        "manualDescription": "These items address areas which an automated testing tool cannot cover. Learn more in our guide on [conducting an accessibility review](https://developers.google.com/web/fundamentals/accessibility/how-to-review)."
      },
      {
        "id": "best-practices",
        "title": "Best Practices",
        "score": 92
      },
      {
        "id": "seo",
        "title": "SEO",
        "description": "These checks ensure that your page is optimized for search engine results ranking. There are additional factors Lighthouse does not check that may affect your search ranking. [Learn more](https://support.google.com/webmasters/answer/35769).",
        "score": 100,
        "manualDescription": "Run these additional validators on your site to check additional SEO best practices."
      },
      {
        "id": "observatory",
        "title": "Security",
        "score": 45,
        "grade": "D-",
        "description": "The Mozilla Observatory teaches you how to configure your sites safely and securely. https://observatory.mozilla.org"
      }
    ]
  },
  {
    "id": "barum",
    "name": "Bærum",
    "url": "https://www.baerum.kommune.no",
    "date": "2019-04-26T00:31:18.874Z",
    "timeStamp": 1556238678874,
    "result": [
      {
        "id": "performance",
        "title": "Performance",
        "score": 80
      },
      {
        "id": "accessibility",
        "title": "Accessibility",
        "description": "These checks highlight opportunities to [improve the accessibility of your web app](https://developers.google.com/web/fundamentals/accessibility). Only a subset of accessibility issues can be automatically detected so manual testing is also encouraged.",
        "score": 76,
        "manualDescription": "These items address areas which an automated testing tool cannot cover. Learn more in our guide on [conducting an accessibility review](https://developers.google.com/web/fundamentals/accessibility/how-to-review)."
      },
      {
        "id": "best-practices",
        "title": "Best Practices",
        "score": 92
      },
      {
        "id": "seo",
        "title": "SEO",
        "description": "These checks ensure that your page is optimized for search engine results ranking. There are additional factors Lighthouse does not check that may affect your search ranking. [Learn more](https://support.google.com/webmasters/answer/35769).",
        "score": 100,
        "manualDescription": "Run these additional validators on your site to check additional SEO best practices."
      },
      {
        "id": "observatory",
        "title": "Security",
        "score": 0,
        "grade": "F",
        "description": "The Mozilla Observatory teaches you how to configure your sites safely and securely. https://observatory.mozilla.org"
      }
    ]
  },
  {
    "id": "bodo",
    "name": "Bodø",
    "url": "https://bodo.kommune.no",
    "date": "2019-04-26T00:31:32.213Z",
    "timeStamp": 1556238692213,
    "result": [
      {
        "id": "performance",
        "title": "Performance",
        "score": 74
      },
      {
        "id": "accessibility",
        "title": "Accessibility",
        "description": "These checks highlight opportunities to [improve the accessibility of your web app](https://developers.google.com/web/fundamentals/accessibility). Only a subset of accessibility issues can be automatically detected so manual testing is also encouraged.",
        "score": 62,
        "manualDescription": "These items address areas which an automated testing tool cannot cover. Learn more in our guide on [conducting an accessibility review](https://developers.google.com/web/fundamentals/accessibility/how-to-review)."
      },
      {
        "id": "best-practices",
        "title": "Best Practices",
        "score": 69
      },
      {
        "id": "seo",
        "title": "SEO",
        "description": "These checks ensure that your page is optimized for search engine results ranking. There are additional factors Lighthouse does not check that may affect your search ranking. [Learn more](https://support.google.com/webmasters/answer/35769).",
        "score": 90,
        "manualDescription": "Run these additional validators on your site to check additional SEO best practices."
      },
      {
        "id": "observatory",
        "title": "Security",
        "score": 0,
        "grade": "F",
        "description": "The Mozilla Observatory teaches you how to configure your sites safely and securely. https://observatory.mozilla.org"
      }
    ]
  },
  {
    "id": "bergen",
    "name": "Bergen",
    "url": "https://www.bergen.kommune.no",
    "date": "2019-04-26T00:31:47.531Z",
    "timeStamp": 1556238707531,
    "result": [
      {
        "id": "performance",
        "title": "Performance",
        "score": 46
      },
      {
        "id": "accessibility",
        "title": "Accessibility",
        "description": "These checks highlight opportunities to [improve the accessibility of your web app](https://developers.google.com/web/fundamentals/accessibility). Only a subset of accessibility issues can be automatically detected so manual testing is also encouraged.",
        "score": 91,
        "manualDescription": "These items address areas which an automated testing tool cannot cover. Learn more in our guide on [conducting an accessibility review](https://developers.google.com/web/fundamentals/accessibility/how-to-review)."
      },
      {
        "id": "best-practices",
        "title": "Best Practices",
        "score": 85
      },
      {
        "id": "seo",
        "title": "SEO",
        "description": "These checks ensure that your page is optimized for search engine results ranking. There are additional factors Lighthouse does not check that may affect your search ranking. [Learn more](https://support.google.com/webmasters/answer/35769).",
        "score": 97,
        "manualDescription": "Run these additional validators on your site to check additional SEO best practices."
      },
      {
        "id": "observatory",
        "title": "Security",
        "score": 0,
        "grade": "F",
        "description": "The Mozilla Observatory teaches you how to configure your sites safely and securely. https://observatory.mozilla.org"
      }
    ]
  },
  {
    "id": "asker",
    "name": "Asker",
    "url": "https://www.asker.kommune.no",
    "date": "2019-04-26T00:32:02.925Z",
    "timeStamp": 1556238722925,
    "result": [
      {
        "id": "performance",
        "title": "Performance",
        "score": 53
      },
      {
        "id": "accessibility",
        "title": "Accessibility",
        "description": "These checks highlight opportunities to [improve the accessibility of your web app](https://developers.google.com/web/fundamentals/accessibility). Only a subset of accessibility issues can be automatically detected so manual testing is also encouraged.",
        "score": 86,
        "manualDescription": "These items address areas which an automated testing tool cannot cover. Learn more in our guide on [conducting an accessibility review](https://developers.google.com/web/fundamentals/accessibility/how-to-review)."
      },
      {
        "id": "best-practices",
        "title": "Best Practices",
        "score": 85
      },
      {
        "id": "seo",
        "title": "SEO",
        "description": "These checks ensure that your page is optimized for search engine results ranking. There are additional factors Lighthouse does not check that may affect your search ranking. [Learn more](https://support.google.com/webmasters/answer/35769).",
        "score": 100,
        "manualDescription": "Run these additional validators on your site to check additional SEO best practices."
      },
      {
        "id": "observatory",
        "title": "Security",
        "score": 0,
        "grade": "F",
        "description": "The Mozilla Observatory teaches you how to configure your sites safely and securely. https://observatory.mozilla.org"
      }
    ]
  }
]